[
    {
        "title":"Fest Website",
        "imgsrc":"projectImg/stepcone.png",
        "demo":"https://gmrit.edu.in/stepcone/",
        "source":"https://gmrit.edu.in/stepcone/"
    },
    {
        "title":"Weather Application",
        "imgsrc":"projectImg/weather.png",
        "demo":"https://github.com/VamsiHanumantu/weather-APP",
        "source":"https://github.com/VamsiHanumantu/weather-APP"
    },
    {
        "title":"Food Website",
        "imgsrc":"projectImg/food.png",
        "demo":"https://github.com/VamsiHanumantu/Food-App",
        "source":"https://github.com/VamsiHanumantu/Food-App"
    }
    
]